nose_watcher/__init__.py
nose_watcher/nose_watcher.py
nose_watcher-0.1.3.dist-info/top_level.txt
nose_watcher-0.1.3.dist-info/entry_points.txt
nose_watcher-0.1.3.dist-info/METADATA
nose_watcher-0.1.3.dist-info/DESCRIPTION.rst
nose_watcher-0.1.3.dist-info/metadata.json
nose_watcher-0.1.3.dist-info/WHEEL
nose_watcher-0.1.3.dist-info/RECORD
