Metadata-Version: 2.0
Name: nose-watcher
Version: 0.1.3
Summary: A nose plugin to watch for changes within the local directory.
Home-page: https://github.com/solarnz/nose-watcher
Author: Chris Trotman
Author-email: chris@trotman.io
License: BSD
Keywords: nose-watcher
Platform: UNKNOWN
Classifier: Development Status :: 4 - Beta
Classifier: Intended Audience :: Developers
Classifier: License :: OSI Approved :: BSD License
Classifier: Natural Language :: English
Classifier: Programming Language :: Python :: 2
Classifier: Programming Language :: Python :: 2.7
Classifier: Programming Language :: Python :: 3
Classifier: Programming Language :: Python :: 3.3
Classifier: Programming Language :: Python :: 3.4
Classifier: Topic :: Software Development :: Testing
Requires-Dist: python-inotify (==0.6-test)
